clockifytool/__init__.py
clockifytool/api.py
clockifytool/app.py
clockifytool/cli.py
clockifytool/commands.py
clockifytool/helpers.py
clockifytool-0.1.0.data/scripts/cft
clockifytool-0.1.0.dist-info/LICENSE
clockifytool-0.1.0.dist-info/METADATA
clockifytool-0.1.0.dist-info/WHEEL
clockifytool-0.1.0.dist-info/top_level.txt
clockifytool-0.1.0.dist-info/RECORD
