Metadata-Version: 2.1
Name: clockifytool
Version: 0.1.0
Summary: Tool to list, create, and delete time entries in Clockify
Home-page: https://github.com/artefactual-labs/clockify-tool
Author: Mike Cantelon
Author-email: mcantelon@gmail.com
License: MIT
Keywords: clockify
License-File: LICENSE
Requires-Dist: isodate
Requires-Dist: python-dateutil
Requires-Dist: PyYAML
Requires-Dist: requests
Requires-Dist: tzlocal ==2.1
